soba/__init__.py
soba/run.py
soba/agents/avatar.py
soba/agents/continuousOccupant.py
soba/agents/occupant.py
soba/agents/roomsOccupant.py
soba/agents/resources/aStar.py
soba/agents/resources/behaviourMarkov.py
soba/agents/resources/fov.py
soba/launchers/listener.py
soba/launchers/visual.py
soba/models/continuousModel.py
soba/models/generalModel.py
soba/models/roomsModel.py
soba/models/timeControl.py
soba/space/continuousElements.py
soba/space/roomsElements.py
soba/visualization/drawModelBack.py
soba/visualization/drawModelFront.js
soba/visualization/favicon.ico
soba/visualization/lib/Chart.min.js
soba/visualization/lib/canvasjs.min.js
soba/visualization/lib/dat.gui.min.js
soba/visualization/lib/jquery.min.js
soba/visualization/ramen/mapGenerator.py
soba/visualization/ramen/performanceGenerator.py
soba-3.4.dist-info/DESCRIPTION.rst
soba-3.4.dist-info/METADATA
soba-3.4.dist-info/RECORD
soba-3.4.dist-info/WHEEL
soba-3.4.dist-info/metadata.json
soba-3.4.dist-info/top_level.txt
