Metadata-Version: 2.0
Name: soba
Version: 3.4
Summary: Simulator of Occupancy Based on Agent
Home-page: https://github.com/gsi-upm/soba
Author: GSI - UPM
Author-email: eduardo.merinom13@gmail.com
License: MIT
Keywords: simulation agents crowds
Platform: UNKNOWN
Classifier: Intended Audience :: Developers
Classifier: Topic :: Software Development :: Build Tools
Classifier: License :: OSI Approved :: MIT License
Classifier: Programming Language :: Python :: 3.3
Classifier: Programming Language :: Python :: 3.4
Classifier: Programming Language :: Python :: 3.5
Requires-Python: >=3
Requires-Dist: numpy
Requires-Dist: anaconda-client
Requires-Dist: tqdm
Requires-Dist: mesa
Requires-Dist: transitions
Requires-Dist: tornado (==4.5.3)
Requires-Dist: pandas
